sqliter/__init__.py
sqliter/constants.py
sqliter/exceptions.py
sqliter/helpers.py
sqliter/model/__init__.py
sqliter/model/foreign_key.py
sqliter/model/model.py
sqliter/model/unique.py
sqliter/orm/__init__.py
sqliter/orm/fields.py
sqliter/orm/foreign_key.py
sqliter/orm/m2m.py
sqliter/orm/model.py
sqliter/orm/query.py
sqliter/orm/registry.py
sqliter/py.typed
sqliter/query/__init__.py
sqliter/query/query.py
sqliter/sqliter.py
sqliter/tui/__init__.py
sqliter/tui/__main__.py
sqliter/tui/app.py
sqliter/tui/demos/__init__.py
sqliter/tui/demos/base.py
sqliter/tui/demos/caching.py
sqliter/tui/demos/connection.py
sqliter/tui/demos/constraints.py
sqliter/tui/demos/crud.py
sqliter/tui/demos/errors.py
sqliter/tui/demos/field_selection.py
sqliter/tui/demos/filters.py
sqliter/tui/demos/models.py
sqliter/tui/demos/ordering.py
sqliter/tui/demos/orm.py
sqliter/tui/demos/results.py
sqliter/tui/demos/string_filters.py
sqliter/tui/demos/timestamps.py
sqliter/tui/demos/transactions.py
sqliter/tui/runner.py
sqliter/tui/styles/app.tcss
sqliter/tui/widgets/__init__.py
sqliter/tui/widgets/code_display.py
sqliter/tui/widgets/demo_list.py
sqliter/tui/widgets/output_display.py
sqliter_py-0.17.0.dist-info/WHEEL
sqliter_py-0.17.0.dist-info/entry_points.txt
sqliter_py-0.17.0.dist-info/METADATA
sqliter_py-0.17.0.dist-info/RECORD
