Metadata-Version: 2.4
Name: sqliter-py
Version: 0.17.0
Summary: Interact with SQLite databases using Python and Pydantic
Author: Grant Ramsay
Author-email: Grant Ramsay <grant@gnramsay.com>
License-Expression: MIT
Classifier: Development Status :: 4 - Beta
Classifier: Intended Audience :: Developers
Classifier: License :: OSI Approved :: MIT License
Classifier: Operating System :: OS Independent
Classifier: Programming Language :: Python :: 3
Classifier: Programming Language :: Python :: 3.9
Classifier: Programming Language :: Python :: 3.10
Classifier: Programming Language :: Python :: 3.11
Classifier: Programming Language :: Python :: 3.12
Classifier: Programming Language :: Python :: 3.13
Classifier: Programming Language :: Python :: 3.14
Classifier: Topic :: Database :: Front-Ends
Classifier: Topic :: Software Development
Classifier: Topic :: Software Development :: Libraries :: Python Modules
Requires-Dist: pydantic>=2.12.5
Requires-Dist: textual>=7.3.0 ; extra == 'demo'
Requires-Dist: inflect==7.0.0 ; extra == 'extras'
Requires-Dist: inflect>=7.0.0 ; extra == 'full'
Requires-Dist: textual>=7.3.0 ; extra == 'full'
Requires-Python: >=3.9
Project-URL: Homepage, http://sqliter.grantramsay.dev
Project-URL: Pull Requests, https://github.com/seapagan/sqliter-py/pulls
Project-URL: Bug Tracker, https://github.com/seapagan/sqliter-py/issues
Project-URL: Changelog, https://github.com/seapagan/sqliter-py/blob/main/CHANGELOG.md
Project-URL: Repository, https://github.com/seapagan/sqliter-py
Provides-Extra: demo
Provides-Extra: extras
Provides-Extra: full
